Lab5/arith_machine.v
// mips_decode: a decoder for MIPS arithmetic instructions
//
// alu_op      (output) - control signal to be sent to the ALU
// writeenable (output) - should a new value be captured by the register file
// itype       (output) - should the ALU receive 1 reg. value and 1 immediate (1) or 2 reg values (0)
// except      (output) - set to 1 when 
// opcode       (input) - the opcode field from the instruction
// funct        (input) - the function field from the instruction
//

module mips_decode(alu_op, writeenable, itype, except, opcode, funct);
   output [2:0] alu_op;
   output 	writeenable, itype, except;
   input  [5:0] opcode, funct;
   wire [5:0] read;
   wire xor10;
   wire 	add, sub, andd, orr, norr, xorr, addi, andi, ori, xori;
   
   assign add = (opcode == `OP_OTHER0) & (funct == `OP0_ADD);
   //assign add = (funct == `OP0_ADD);
   assign sub = (opcode == `OP_OTHER0) & (funct == `OP0_SUB);
   //assign sub = (funct == `OP0_SUB);
   assign andd = (opcode == `OP_OTHER0) & (funct == `OP0_AND);
   //assign andd = (funct == `OP0_AND);
   assign orr = (opcode == `OP_OTHER0) & (funct == `OP0_OR);
   //assign orr = (funct == `OP0_OR);
   assign norr = (opcode == `OP_OTHER0) & (funct == `OP0_NOR);
   //assign norr = (funct == `OP0_NOR);
   assign xorr = (opcode == `OP_OTHER0) & (funct == `OP0_XOR);
   //assign xorr = (funct == `OP0_XOR);
   //assign addi = (opcode == `OP_ADDI) & (funct == `OP_OTHER0);
   assign addi = (opcode == `OP_ADDI) ;
   //assign andi = (opcode == `OP_ANDI) & (funct == `OP_OTHER0);
   assign andi = (opcode == `OP_ANDI);
   //assign ori = (opcode == `OP_ORI) & (funct == `OP_OTHER0);
   assign ori = (opcode == `OP_ORI);
   //assign xori = (opcode == `OP_XORI) & (funct == `OP_OTHER0);
   assign xori = (opcode == `OP_XORI);
   assign alu_op[2] = (!add & !sub) & (!addi);
   assign alu_op[1] = ~(((andd|orr)|andi)|ori);
   assign alu_op[0] = sub|orr|xorr|ori|xori;
   assign except = (!add&!sub&!andd&!orr&!norr&!xorr&!addi&!andi&!ori&!xori);
   assign writeenable = 1'b1;
   assign itype = addi|andi|ori|xori;
endmodule // mips_decode

// arith_machine: execute a series of arithmetic instructions from an instruction cache
//
// except (output) - set to 1 when an unrecognized instruction is to be executed.
// clk     (input) - the clock signal
// reset   (input) - set to 1 to set all registers to zero, set to 0 for normal execution.

module arith_machine(except, clk, reset);
   output 	except;
   input        clk, reset;

   wire [31:0] 	inst;  
   wire [31:0] 	PC;  
   wire [4:0]	Rdest;
   wire 		itype, wr_en, overflow, zero, negative;
   wire [2:0]	alu_op;
   wire [31:0]	rtData, out, imm32, A, B, nextPC;

   register #(32) PC_reg(PC, nextPC, clk, 1, reset);
   alu32 alu0(nextPC, overflow, zero, negative, PC, 32'b100, 3'b10);
   
   
   /* add other modules */
   mips_decode mip0(alu_op, wr_en, itype, except, inst[31:26], inst[5:0]);
   instruction_memory im(PC[31:2], inst);
   regfile rf (inst[25:21], inst[20:16], Rdest, A, rtData, out, wr_en, clk, reset);
   mux2v #(5) itype0(Rdest, inst[15:11], inst[20:16], itype);
   mux2v itype1(B, rtData, imm32, itype);
   assign imm32 = {{16{inst[15]}}, inst[15:0]};//Sign extender
   alu32 main_alu(out, overflow, zero, negative, A, B, alu_op);
endmodule // arith_machine

Lab5/mips_tb.v
module testThis;
	reg [5:0] opcode = 0;
	reg [5:0] funct = 0;

	initial begin
		$dumpfile("mips.vcd");
		$dumpvars(0, testThis);
		
		# 1 funct = 6'b100000;
		# 1 funct = 6'b100010;
		# 1 funct = 6'b100100;
		# 1 funct = 6'b100101;
		# 1 funct = 6'b100110;
		# 1 funct = 6'b100111;
		# 1 funct = 6'b0; opcode = 6'b001000;
		# 1 opcode = 6'b001100;
		# 1 opcode = 6'b001101;
		# 1 opcode = 6'b001110; 
		# 1 funct = 6'b100000;
		# 1 $finish;
	end

	wire except, wr_en, itype;
	wire [2:0] alu;
	mips_decode m0(alu, wr_en, itype, except, opcode, funct);

	initial begin
		//$display("add	sub	n	o	n	x	addi	andi	ori	xori	alu_op");
		//$monitor("%b	%b	%b	%b	%b	%b	%b	%b	%b	%b	%b", m0.add, m0.sub, m0.andd, m0.orr, m0.norr, m0.xorr, m0.addi, m0.andi, m0.ori, m0.xori, alu);
		$display("alu_op	itype	wr_en	except	opcode	funct");
		$monitor("%d	%d	%d	%d	%h	%h -at time %t", alu, itype, wr_en, except, opcode, funct, $time);
	end

endmodule

Lab5/mips.vcd
$date
	Sun Feb 17 16:07:21 2013
$end
$version
	Icarus Verilog
$end
$timescale
	1s
$end
$scope module testThis $end
$var wire 3 ! alu [2:0] $end
$var wire 1 " except $end
$var wire 1 # itype $end
$var wire 1 $ wr_en $end
$var reg 6 % funct [5:0] $end
$var reg 6 & opcode [5:0] $end
$scope module m0 $end
$var wire 1 ' add $end
$var wire 1 ( addi $end
$var wire 3 ) alu_op [2:0] $end
$var wire 1 * andd $end
$var wire 1 + andi $end
$var wire 1 " except $end
$var wire 6 , funct [5:0] $end
$var wire 1 # itype $end
$var wire 1 - norr $end
$var wire 6 . opcode [5:0] $end
$var wire 1 / ori $end
$var wire 1 0 orr $end
$var wire 1 1 sub $end
$var wire 1 $ writeenable $end
$var wire 1 2 xori $end
$var wire 1 3 xorr $end
$upscope $end
$upscope $end
$enddefinitions $end
#0
$dumpvars
03
02
01
00
0/
b0 .
0-
b0 ,
0+
0*
b110 )
0(
0'
b0 &
b0 %
1$
0#
1"
b110 !
$end
#1
0"
b10 !
b10 )
b100000 %
b100000 ,
1'
#2
b11 !
b11 )
b100010 %
b100010 ,
0'
11
#3
b100 !
b100 )
b100100 %
b100100 ,
01
1*
#4
b101 !
b101 )
b100101 %
b100101 ,
0*
10
#5
b111 !
b111 )
b100110 %
b100110 ,
00
13
#6
0"
b110 !
b110 )
b100111 %
b100111 ,
1-
03
#7
1#
b10 !
b10 )
b1000 &
b1000 .
1(
b0 %
b0 ,
0-
#8
b100 !
b100 )
b1100 &
b1100 .
0(
1+
#9
b101 !
b101 )
b1101 &
b1101 .
0+
1/
#10
b111 !
b111 )
b1110 &
b1110 .
0/
12
#11
b11 !
b11 )
b100000 %
b100000 ,
1'
